{"_ts":[1591139152,1591192984],"_r":{"breakdown":{"html":{"bytes":[73415,75566],"requests":[6,12]},"js":{"bytes":[112954,85369],"requests":[21,23]},"css":{"bytes":[62122,60431],"requests":[16,15]},"image":{"bytes":[11552,25363],"requests":[3,5]},"flash":{"bytes":[0,0],"requests":[0,0]},"font":{"bytes":[0,0],"requests":[0,0]},"video":{"bytes":[0,0],"requests":[0,0]},"other":{"bytes":[2046,2615],"requests":[2,4]}},"date":[1591139152,1591192984],"domElements":[375,376],"domInteractive":[10489,29365],"firstPaint":[10458,23399],"fullyLoaded":[16952,39466],"id":["200602_CF_82282f4b15850c95e3a8c580dc994513","200603_WX_648d098b7ccfe093d39e318cb7b3c2c4"],"loadTime":[10586,29428],"render":[10500,23500],"SpeedIndex":[10500,23500],"TTFB":[4446,2993],"videoFrames":[[{"_i":"ms_000000.jpg","_t":0,"_vc":0},{"_i":"ms_010500.jpg","_t":10500,"_vc":100}],[{"_i":"ms_000000.jpg","_t":0,"_vc":0},{"_i":"ms_023500.jpg","_t":23500,"_vc":100}]],"visualComplete":[10500,23500],"lighthouse":[null,null],"pagespeed":[null,null]}}