{"_ts":[1601515192],"_r":{"breakdown":{"html":{"bytes":[22551],"requests":[3]},"js":{"bytes":[110232],"requests":[22]},"css":{"bytes":[74258],"requests":[17]},"image":{"bytes":[38156],"requests":[8]},"flash":{"bytes":[0],"requests":[0]},"font":{"bytes":[0],"requests":[0]},"video":{"bytes":[0],"requests":[0]},"other":{"bytes":[3555],"requests":[6]}},"date":[1601515192],"domElements":[350],"domInteractive":[4376],"firstPaint":[4233],"fullyLoaded":[16878],"id":["201001_Di3X_1195a9990cdc758ef77fc27ca55f2c4b"],"loadTime":[4461],"render":[4300],"SpeedIndex":[4304],"TTFB":[3769],"videoFrames":[[{"_i":"ms_000000.jpg","_t":0,"_vc":0},{"_i":"ms_004300.jpg","_t":4300,"_vc":98},{"_i":"ms_004400.jpg","_t":4400,"_vc":98},{"_i":"ms_004500.jpg","_t":4500,"_vc":100}]],"visualComplete":[4500],"lighthouse":[null],"pagespeed":[null]}}