{"_ts":[1598984132,1599036817,1599104891],"_r":{"breakdown":{"html":{"bytes":[27249,27508,28124],"requests":[3,3,4]},"js":{"bytes":[115363,111503,111503],"requests":[24,23,23]},"css":{"bytes":[73927,74203,74203],"requests":[17,17,17]},"image":{"bytes":[38177,38177,38177],"requests":[8,8,8]},"flash":{"bytes":[0,0,0],"requests":[0,0,0]},"font":{"bytes":[0,0,0],"requests":[0,0,0]},"video":{"bytes":[0,0,0],"requests":[0,0,0]},"other":{"bytes":[5403,5403,5403],"requests":[7,7,7]}},"date":[1598984132,1599036817,1599104891],"domElements":[465,465,465],"domInteractive":[8115,8854,12364],"firstPaint":[6625,7383,10979],"fullyLoaded":[27385,31922,32117],"id":["200901_3C_f44ad36aa85d2f43fe3ef880c7fb6445","200902_RQ_e713f052175f397863df1a56ee89cfed","200903_6G_17b99b856686317c493d202b1ceef5c5"],"loadTime":[8195,8917,12439],"render":[6700,7400,11000],"SpeedIndex":[6700,7402,11002],"TTFB":[5191,5913,9613],"videoFrames":[[{"_i":"ms_000000.jpg","_t":0,"_vc":0},{"_i":"ms_006700.jpg","_t":6700,"_vc":100}],[{"_i":"ms_000000.jpg","_t":0,"_vc":0},{"_i":"ms_007400.jpg","_t":7400,"_vc":98},{"_i":"ms_007500.jpg","_t":7500,"_vc":100}],[{"_i":"ms_000000.jpg","_t":0,"_vc":0},{"_i":"ms_011000.jpg","_t":11000,"_vc":98},{"_i":"ms_011100.jpg","_t":11100,"_vc":100}]],"visualComplete":[6700,7500,11100],"lighthouse":[null,null,null],"pagespeed":[null,null,null]}}