{"_ts":[1590973270,1591028200,1591076835],"_r":{"breakdown":{"html":{"bytes":[34664,34664,95722],"requests":[8,8,8]},"js":{"bytes":[227750,227754,199693],"requests":[37,37,38]},"css":{"bytes":[94429,94429,94429],"requests":[21,21,21]},"image":{"bytes":[38693,38693,38693],"requests":[20,20,20]},"flash":{"bytes":[0,0,0],"requests":[0,0,0]},"font":{"bytes":[14176,14176,14176],"requests":[1,1,1]},"video":{"bytes":[0,0,0],"requests":[0,0,0]},"other":{"bytes":[11059,11058,11070],"requests":[17,17,17]}},"date":[1590973270,1591028200,1591076835],"domElements":[380,380,380],"domInteractive":[13854,13374,12963],"firstPaint":[11592,11191,11010],"fullyLoaded":[37345,37822,38905],"id":["200601_J5_c6d3c1896cff5d5349062dbd3ef5cb79","200601_GT_0d70ca8d0e5a10cb92662882cbcb33f5","200602_PG_a49fbdb386d8f3b5a578c7cdc47bd226"],"loadTime":[17813,17058,16670],"render":[11700,11300,11100],"SpeedIndex":[11723,11322,11121],"TTFB":[9924,9483,9353],"videoFrames":[[{"_i":"ms_000000.jpg","_t":0,"_vc":0},{"_i":"ms_011700.jpg","_t":11700,"_vc":99},{"_i":"ms_011900.jpg","_t":11900,"_vc":99},{"_i":"ms_012000.jpg","_t":12000,"_vc":99},{"_i":"ms_012100.jpg","_t":12100,"_vc":99},{"_i":"ms_012200.jpg","_t":12200,"_vc":99},{"_i":"ms_012900.jpg","_t":12900,"_vc":99},{"_i":"ms_013100.jpg","_t":13100,"_vc":99},{"_i":"ms_013300.jpg","_t":13300,"_vc":99},{"_i":"ms_014000.jpg","_t":14000,"_vc":100}],[{"_i":"ms_000000.jpg","_t":0,"_vc":0},{"_i":"ms_011300.jpg","_t":11300,"_vc":99},{"_i":"ms_011400.jpg","_t":11400,"_vc":99},{"_i":"ms_011500.jpg","_t":11500,"_vc":99},{"_i":"ms_011600.jpg","_t":11600,"_vc":99},{"_i":"ms_011700.jpg","_t":11700,"_vc":99},{"_i":"ms_012500.jpg","_t":12500,"_vc":99},{"_i":"ms_012600.jpg","_t":12600,"_vc":99},{"_i":"ms_012800.jpg","_t":12800,"_vc":99},{"_i":"ms_013500.jpg","_t":13500,"_vc":100}],[{"_i":"ms_000000.jpg","_t":0,"_vc":0},{"_i":"ms_011100.jpg","_t":11100,"_vc":98},{"_i":"ms_011200.jpg","_t":11200,"_vc":99},{"_i":"ms_011300.jpg","_t":11300,"_vc":99},{"_i":"ms_011400.jpg","_t":11400,"_vc":99},{"_i":"ms_011500.jpg","_t":11500,"_vc":99},{"_i":"ms_011600.jpg","_t":11600,"_vc":99},{"_i":"ms_012400.jpg","_t":12400,"_vc":99},{"_i":"ms_012500.jpg","_t":12500,"_vc":99},{"_i":"ms_012800.jpg","_t":12800,"_vc":99},{"_i":"ms_013100.jpg","_t":13100,"_vc":100}]],"visualComplete":[14000,13500,13100],"lighthouse":[null,null,null],"pagespeed":[null,null,null]}}