{"_ts":[1601514341],"_r":{"breakdown":{"html":{"bytes":[24779],"requests":[3]},"js":{"bytes":[111545],"requests":[23]},"css":{"bytes":[74258],"requests":[17]},"image":{"bytes":[176349],"requests":[10]},"flash":{"bytes":[0],"requests":[0]},"font":{"bytes":[0],"requests":[0]},"video":{"bytes":[0],"requests":[0]},"other":{"bytes":[6340],"requests":[9]}},"date":[1601514341],"domElements":[431],"domInteractive":[5390],"firstPaint":[3994],"fullyLoaded":[24915],"id":["201001_DiSN_e4a8967005c75c42c4fdbece10d23ab4"],"loadTime":[5477],"render":[4100],"SpeedIndex":[4516],"TTFB":[2614],"videoFrames":[[{"_i":"ms_000000.jpg","_t":0,"_vc":0},{"_i":"ms_004100.jpg","_t":4100,"_vc":48},{"_i":"ms_004200.jpg","_t":4200,"_vc":48},{"_i":"ms_004400.jpg","_t":4400,"_vc":48},{"_i":"ms_004900.jpg","_t":4900,"_vc":100}]],"visualComplete":[4900],"lighthouse":[null],"pagespeed":[null]}}