{"_ts":[1590988682],"_r":{"breakdown":{"html":{"bytes":[21871],"requests":[3]},"js":{"bytes":[98636],"requests":[24]},"css":{"bytes":[62223],"requests":[17]},"image":{"bytes":[52906],"requests":[9]},"flash":{"bytes":[0],"requests":[0]},"font":{"bytes":[0],"requests":[0]},"video":{"bytes":[0],"requests":[0]},"other":{"bytes":[2170],"requests":[3]}},"date":[1590988682],"domElements":[392],"domInteractive":[2753],"firstPaint":[2701],"fullyLoaded":[13479],"id":["200601_8T_e19d69487a59b9bc70cb5f3f91de4f58"],"loadTime":[2879],"render":[2800],"SpeedIndex":[2800],"TTFB":[2250],"videoFrames":[[{"_i":"ms_000000.jpg","_t":0,"_vc":0},{"_i":"ms_002800.jpg","_t":2800,"_vc":100}]],"visualComplete":[2800],"lighthouse":[null],"pagespeed":[null]}}