{"_ts":[1596245120],"_r":{"breakdown":{"html":{"bytes":[89752],"requests":[5]},"js":{"bytes":[138015],"requests":[26]},"css":{"bytes":[104952],"requests":[20]},"image":{"bytes":[38177],"requests":[8]},"flash":{"bytes":[0],"requests":[0]},"font":{"bytes":[14176],"requests":[1]},"video":{"bytes":[0],"requests":[0]},"other":{"bytes":[5407],"requests":[7]}},"date":[1596245120],"domElements":[384],"domInteractive":[11765],"firstPaint":[10705],"fullyLoaded":[31599],"id":["200801_WH_26683cea99ec4a347aa2477f57758319"],"loadTime":[12290],"render":[10800],"SpeedIndex":[10800],"TTFB":[9017],"videoFrames":[[{"_i":"ms_000000.jpg","_t":0,"_vc":0},{"_i":"ms_010800.jpg","_t":10800,"_vc":100},{"_i":"ms_011000.jpg","_t":11000,"_vc":100},{"_i":"ms_011400.jpg","_t":11400,"_vc":100},{"_i":"ms_011600.jpg","_t":11600,"_vc":100},{"_i":"ms_011700.jpg","_t":11700,"_vc":100},{"_i":"ms_011900.jpg","_t":11900,"_vc":100},{"_i":"ms_012300.jpg","_t":12300,"_vc":100}]],"visualComplete":[10800],"lighthouse":[null],"pagespeed":[null]}}