{"_ts":[1596354074],"_r":{"breakdown":{"html":{"bytes":[90014],"requests":[4]},"js":{"bytes":[128225],"requests":[25]},"css":{"bytes":[103048],"requests":[19]},"image":{"bytes":[60703],"requests":[10]},"flash":{"bytes":[0],"requests":[0]},"font":{"bytes":[0],"requests":[0]},"video":{"bytes":[0],"requests":[0]},"other":{"bytes":[5403],"requests":[7]}},"date":[1596354074],"domElements":[394],"domInteractive":[8556],"firstPaint":[7015],"fullyLoaded":[31684],"id":["200802_FW_160abb55279aa921257197c0cb90fc69"],"loadTime":[8637],"render":[7000],"SpeedIndex":[7103],"TTFB":[5579],"videoFrames":[[{"_i":"ms_000000.jpg","_t":0,"_vc":0},{"_i":"ms_007000.jpg","_t":7000,"_vc":67},{"_i":"ms_007100.jpg","_t":7100,"_vc":67},{"_i":"ms_007200.jpg","_t":7200,"_vc":83},{"_i":"ms_007300.jpg","_t":7300,"_vc":86},{"_i":"ms_007400.jpg","_t":7400,"_vc":94},{"_i":"ms_007500.jpg","_t":7500,"_vc":100}]],"visualComplete":[7500],"lighthouse":[null],"pagespeed":[null]}}